pystructlayout/__init__.py
pystructlayout/structure.py
pystructlayout-1.0.0.dist-info/licenses/LICENSE.txt
pystructlayout-1.0.0.dist-info/METADATA
pystructlayout-1.0.0.dist-info/WHEEL
pystructlayout-1.0.0.dist-info/top_level.txt
pystructlayout-1.0.0.dist-info/RECORD
