Metadata-Version: 2.4
Name: PyStructLayout
Version: 1.0.0
Summary: A decorator-based system for defining and validating binary struct layouts in Python.
Author-email: WCG847 <heelmods@gmail.com>
Keywords: struct,binary,decorator,layout,unpack
Classifier: Programming Language :: Python :: 3
Classifier: Operating System :: OS Independent
Classifier: Topic :: Software Development :: Libraries
Classifier: Topic :: Software Development :: Code Generators
Requires-Python: >=3.13
License-File: LICENSE.txt
Dynamic: license-file
